Workbook

Sheet Лист1
B1: Показатели | C1: Усл. обозн | D1: 2024 | E1: 2025
A2: 1 | B2: Годовой объем оборота(Выручка), млн. руб. | C2: Т | D2: 40850.5 | E2: 47632.5
A3: 2 | B3: Однодневный оборот, млн. руб. | C3: То | D3: 111.9 | E3: 130.5
A4: 3 | B4: Чистая прибыль, млн. руб. | C4: Пч | D4: 1686.4 | E4: 1776.4
A5: 4 | B5: Прибыль от продаж, млн. руб. | C5: Пп | D5: 11722.1 | E5: 13910.9
A6: 5 | B6: Издержки обращения, млн. руб. | C6: ИО | D6: 9699.9 | E6: 13132
A7: 6 | B7: Себестоимость продаж, млн. руб. | C7: Сс | D7: 29128.4 | E7: 33721.6
A8: 7 | B8: Запасы на начало года, млн. руб. | C8: Знг | D8: 7596.6 | E8: 9094.7
A9: 8 | B9: Запасы на конец года млн. руб. | C9: Зкг | D9: 9094.7 | E9: 9648.6
A10: 9 | B10: Дебиторская задолженность млн. руб. | C10: ДЗ | D10: 1296.5 | E10: 3410.8
A11: 10 | B11: Денежные средства млн. руб. | C11: ДС | D11: 263.9 | E11: 470.4
A12: 11 | B12: Краткосрочная задолженность, млн. руб. | C12: КЗ | D12: 7972.1 | E12: 8773.2
A13: 12 | B13: Собственный капитал, млн. руб. | C13: СК | D13: 9728.4 | E13: 9993.1
... A16: 15 | B16: Оборотные активы, млн. руб. | C16: ОА | D16: 12348.5 | E16: 13960.6

Sheet Лист2
B1: Показатели | C1: Усл. обозн. | D1: 2024 | E1: 2025
A2: 1 | B2: Рентабельность продаж,% | C2: Рп | D2: =Лист1!D4/Лист1!D2 -> 0.041282236 | E2: =Лист1!E4/Лист1!E2 -> 0.037293864
A3: 2 | B3: Рентабельность коммерческой деятельности, % | C3: Ркд | D3: =Лист1!D5/Лист1!D2 -> 0.2869512 | E3: =Лист1!E5/Лист1!E2 -> 0.2920464
A4: 3 | B4: Рентабельность затрат | C4: Рз | D4: =Лист1!D4/Лист1!D6 -> 0.17385746 | E4: =Лист1!E4/Лист1!E6 -> 0.13527262
A5: 4 | B5: Рентабельность собственного капитала, % | C5: ROE | D5: =Лист1!D4/Лист1!D13 -> 0.17334814 | E5: =Лист1!E4/Лист1!E13 -> 0.17776266
A6: 5 | B6: Средние товарные запасы, тыс. руб. | C6: ТЗ | D6: =(Лист1!D8+Лист1!D9)/2 -> 8345.65 | E6: =(Лист1!E8+Лист1!E9)/2 -> 9371.65
A7: 6 | B7: Оборачиваемость товарных запасов, дни | C7: ТЗ | D7: =365/D8 -> 74.568543 | E7: =365/E8 -> 71.81341
A8: 7 | B8: Оборачиваемость товарных запасов, раз | C8: Ор | D8: =Лист1!D2/D6 -> 4.8948254 | E8: =Лист1!E2/E6 -> 5.0826162
A9: 8 | B9: Оборачиваемость дебиторской задолженности, дни | C9: Дз | D9: =(Лист1!D10/Лист1!D5)*365 -> 40.370113 | E9: =(Лист1!E10/Лист1!E5)*365 -> 89.493994
A10: 9 | B10: Коэффициент текущей ликвидности | C10: Тл | D10: =Лист1!D16/Лист1!D12 -> 1.5489645 | E10: =Лист1!E16/Лист1!E12 -> 1.591278
A11: 10 | B11: Коэффициент абсолютной ликвидности | C11: Ал | D11: =Лист1!D11/Лист1!D12 -> 0.033102947 | E11: =Лист1!E11/Лист1!E12 -> 0.053617836
A12: 11 | B12: Коэффициент финансовой независимости | C12: Кфн | D12: =Лист1!D13/Лист1!D14 -> 0.52019913 | E12: =Лист1!E13/Лист1!E14 -> 0.48809925
A13: 12 | B13: Коэффициент обеспеченности собственными оборотными средствами | C13: Ксо | D13: =(Лист1!D13-Лист1!D15)/Лист1!D16 -> 0.27336924 | E13: =(Лист1!E13-Лист1!E15)/Лист1!E16 -> 0.24928728
A14: 13 | B14: Уровень коммерческих расходов | C14: Укр | D14: =Лист1!D6/Лист1!D2 -> 0.23744875 | E14: =Лист1!E6/Лист1!E2 -> 0.27569412
A15: 14 | B15: Валовая рентабельность | C15: GPM | D15: =(Лист1!D2-Лист1!D7)/Лист1!D2 -> 0.2869512 | E15: =(Лист1!E2-Лист1!E7)/Лист1!E2 -> 0.2920464
B17: Несмотря на уверенный рост выручки, предприятие столкнулось со снижением маржинальности продаж и увеличением доли заемных средств, что требует контроля долговой нагрузки. Положительным моментом является значительное ускорение работы с дебиторской задолженностью, период оборачиваемости которой сократился вдвое, а также улучшение оборачиваемости запасов. Коэффициенты ликвидности демонстрируют небольшое улучшение, однако остаются на уровнях, требующих внимания к абсолютной платежеспособности. Снижение рентабельности затрат сигнализирует о необходимости оптимизации расходов, несмотря на рост общей эффективности бизнес-процессов. Главной стратегической задачей становится повышение финансовой независимости для компенсации рисков, связанных с ростом складских запасов и обязательств. В целом текущая деятельность оценивается положительно благодаря улучшению управления оборотными активами, но финансовая устойчивость нуждается в укреплении.
